{
  "items": [
    {
      "name": "Markdown"
    },
    {
      "name": "Markdown (Hugo)"
    },
    {
      "name": "Html"
    },
    {
      "name": "TextBundle"
    },
    {
      "name": "Typst"
    },
    {
      "name": "PDF"
    },
    {
      "name": "Word (.docx)"
    },
    {
      "name": "OpenOffice"
    },
    {
      "name": "RTF"
    },
    {
      "name": "Epub"
    },
    {
      "name": "Latex"
    },
    {
      "name": "Latex"
    },
    {
      "name": "Media Wiki"
    },
    {
      "name": "reStructuredText"
    },
    {
      "name": "Textile"
    },
    {
      "name": "OPML"
    },
    {
      "name": "Bibliography"
    }
  ],
  "defaultExportDirectoryMode": "Auto",
  "openExportedFile": true,
  "lastExportDirectory": {
    "win32": "C:\\Users\\coleb\\Documents"
  },
  "lastExportType": "Word (.docx)"
}